{
  "num": 26,
  "sumario": "",
  "versiculos": [
    {
      "n": 1,
      "texto": "Mulieris bonæ beatus vir : numerus enim annorum illius duplex."
    },
    {
      "n": 2,
      "texto": "Mulier fortis oblectat virum suum, et annos vitæ illius in pace implebit."
    },
    {
      "n": 3,
      "texto": "Pars bona mulier bona, in parte timentium Deum dabitur viro pro factis bonis :"
    },
    {
      "n": 4,
      "texto": "divitis autem et pauperis cor bonum, in omni tempore vultus illorum hilaris."
    },
    {
      "n": 5,
      "texto": "A tribus timuit cor meum, et in quarto facies mea metuit :"
    },
    {
      "n": 6,
      "texto": "delaturam civitatis, et collectionem populi :"
    },
    {
      "n": 7,
      "texto": "calumniam mendacem super mortem omnia gravia :"
    },
    {
      "n": 8,
      "texto": "dolor cordis et luctus, mulier zelotypa."
    },
    {
      "n": 9,
      "texto": "In muliere zelotypa flagellum linguæ, omnibus communicans."
    },
    {
      "n": 10,
      "texto": "Sicut boum jugum quod movetur, ita et mulier nequam : qui tenet illam quasi qui apprehendit scorpionem."
    },
    {
      "n": 11,
      "texto": "Mulier ebriosa ira magna, et contumelia : et turpitudo illius non tegetur."
    },
    {
      "n": 12,
      "texto": "Fornicatio mulieris in extollentia oculorum, et in palpebris illius agnoscetur."
    },
    {
      "n": 13,
      "texto": "In filia non avertente se, firma custodiam, ne inventa occasione utatur se."
    },
    {
      "n": 14,
      "texto": "Ab omni irreverentia oculorum ejus cave, et ne mireris si te neglexerit."
    },
    {
      "n": 15,
      "texto": "Sicut viator sitiens ad fontem os aperiet, et ab omni aqua proxima bibet, et contra omnem palum sedebit, et contra omnem sagittam aperiet pharetram donec deficiat."
    },
    {
      "n": 16,
      "texto": "Gratia mulieris sedulæ delectabit virum suum, et ossa illius impinguabit."
    },
    {
      "n": 17,
      "texto": "Disciplina illius datum Dei est."
    },
    {
      "n": 18,
      "texto": "Mulier sensata et tacita, non est immutatio eruditæ animæ."
    },
    {
      "n": 19,
      "texto": "Gratia super gratiam mulier sancta et pudorata."
    },
    {
      "n": 20,
      "texto": "Omnis autem ponderatio non est digna continentis animæ."
    },
    {
      "n": 21,
      "texto": "Sicut sol oriens mundo in altissimis Dei, sic mulieris bonæ species in ornamentum domus ejus."
    },
    {
      "n": 22,
      "texto": "Lucerna splendens super candelabrum sanctum, et species faciei super ætatem stabilem."
    },
    {
      "n": 23,
      "texto": "Columnæ aureæ super bases argenteas, et pedes firmi super plantas stabilis mulieris."
    },
    {
      "n": 24,
      "texto": "Fundamenta æterna supra petram solidam, et mandata Dei in corde mulieris sanctæ."
    },
    {
      "n": 25,
      "texto": "In duobus contristatum est cor meum, et in tertio iracundia mihi advenit :"
    },
    {
      "n": 26,
      "texto": "vir bellator deficiens per inopiam ; et vir sensatus contemptus ;"
    },
    {
      "n": 27,
      "texto": "et qui transgreditur a justitia ad peccatum : Deus paravit eum ad rhomphæam."
    },
    {
      "n": 28,
      "texto": "Duæ species difficiles et periculosæ mihi apparuerunt : difficile exuitur negotians a negligentia, et non justificabitur caupo a peccatis labiorum."
    }
  ],
  "notas": {},
  "link": "https://la.wikisource.org/wiki/Vulgata_Clementina/Liber_Ecclesiasticus#Caput_26"
}
