{
  "num": 5,
  "sumario": "Genealogia ab Adam usque ad Noë. Vita et mors patriarcharum ante diluvium.",
  "versiculos": [
    {
      "n": 1,
      "texto": "Hic est liber generationis Adam. In die qua creavit Deus hominem, ad similitudinem Dei fecit illum."
    },
    {
      "n": 2,
      "texto": "Masculum et feminam creavit eos, et benedixit illis : et vocavit nomen eorum Adam, in die quo creati sunt."
    },
    {
      "n": 3,
      "texto": "Vixit autem Adam centum triginta annis : et genuit ad imaginem et similitudinem suam, vocavitque nomen ejus Seth."
    },
    {
      "n": 4,
      "texto": "Et facti sunt dies Adam, postquam genuit Seth, octingenti anni : genuitque filios et filias."
    },
    {
      "n": 5,
      "texto": "Et factum est omne tempus quod vixit Adam, anni nongenti triginta, et mortuus est."
    },
    {
      "n": 6,
      "texto": "Vixit quoque Seth centum quinque annis, et genuit Enos."
    },
    {
      "n": 7,
      "texto": "Vixitque Seth, postquam genuit Enos, octingentis septem annis, genuitque filios et filias."
    },
    {
      "n": 8,
      "texto": "Et facti sunt omnes dies Seth nongentorum duodecim annorum, et mortuus est."
    },
    {
      "n": 9,
      "texto": "Vixit vero Enos nonaginta annis, et genuit Cainan."
    },
    {
      "n": 10,
      "texto": "Post cujus ortum vixit octingentis quindecim annis, et genuit filios et filias."
    },
    {
      "n": 11,
      "texto": "Factique sunt omnes dies Enos nongenti quinque anni, et mortuus est."
    },
    {
      "n": 12,
      "texto": "Vixit quoque Cainan septuaginta annis, et genuit Malaleel."
    },
    {
      "n": 13,
      "texto": "Et vixit Cainan, postquam genuit Malaleel, octingentis quadraginta annis, genuitque filios et filias."
    },
    {
      "n": 14,
      "texto": "Et facti sunt omnes dies Cainan nongenti decem anni, et mortuus est."
    },
    {
      "n": 15,
      "texto": "Vixit autem Malaleel sexaginta quinque annis, et genuit Jared."
    },
    {
      "n": 16,
      "texto": "Et vixit Malaleel, postquam genuit Jared, octingentis triginta annis, genuitque filios et filias."
    },
    {
      "n": 17,
      "texto": "Et facti sunt omnes dies Malaleel octingenti nonaginta quinque anni, et mortuus est."
    },
    {
      "n": 18,
      "texto": "Vixitque Jared centum sexaginta duobus annis, et genuit Henoch."
    },
    {
      "n": 19,
      "texto": "Et vixit Jared, postquam genuit Henoch, octingentis annis, genuitque filios et filias."
    },
    {
      "n": 20,
      "texto": "Et facti sunt omnes dies Jared nongenti sexaginta duo anni, et mortuus est."
    },
    {
      "n": 21,
      "texto": "Porro Henoch vixit sexaginta quinque annis, et genuit Mathusalam."
    },
    {
      "n": 22,
      "texto": "Et ambulavit Henoch cum Deo : et vixit, postquam genuit Mathusalam, trecentis annis, genuitque filios et filias."
    },
    {
      "n": 23,
      "texto": "Et facti sunt omnes dies Henoch trecenti sexaginta quinque anni."
    },
    {
      "n": 24,
      "texto": "Ambulavitque cum Deo, et non apparuit : quia tulit eum Deus."
    },
    {
      "n": 25,
      "texto": "Vixit quoque Mathusala centum octoginta septem annis, et genuit Lamech."
    },
    {
      "n": 26,
      "texto": "Et vixit Mathusala, postquam genuit Lamech, septingentis octoginta duobus annis, genuitque filios et filias."
    },
    {
      "n": 27,
      "texto": "Et facti sunt omnes dies Mathusala nongenti sexaginta novem anni, et mortuus est."
    },
    {
      "n": 28,
      "texto": "Vixit autem Lamech centum octoginta duobus annis, et genuit filium :"
    },
    {
      "n": 29,
      "texto": "vocavitque nomen ejus Noë, dicens : Iste consolabitur nos ab operibus et laboribus manuum nostrarum in terra, cui maledixit Dominus."
    },
    {
      "n": 30,
      "texto": "Vixitque Lamech, postquam genuit Noë, quingentis nonaginta quinque annis, genuitque filios et filias."
    },
    {
      "n": 31,
      "texto": "Et facti sunt omnes dies Lamech septingenti septuaginta septem anni, et mortuus est."
    },
    {
      "n": 32,
      "texto": "Noë vero cum quingentorum esset annorum, genuit Sem, Cham, et Japheth."
    }
  ],
  "notas": {},
  "link": "https://la.wikisource.org/wiki/Vulgata_Clementina/Genesis#Caput_5"
}
