{
  "num": 13,
  "fonte": "https://la.wikisource.org/wiki/Vulgata_Clementina/Evangelium_Secundum_Joannem",
  "versiculos": [
    {
      "n": 1,
      "texto": "Ante diem festum Paschæ, sciens Jesus quia venit hora ejus ut transeat ex hoc mundo ad Patrem : cum dilexisset suos, qui erant in mundo, in finem dilexit eos."
    },
    {
      "n": 2,
      "texto": "Et cœna facta, cum diabolus jam misisset in cor ut traderet eum Judas Simonis Iscariotæ :"
    },
    {
      "n": 3,
      "texto": "sciens quia omnia dedit ei Pater in manus, et quia a Deo exivit, et ad Deum vadit :"
    },
    {
      "n": 4,
      "texto": "surgit a cœna, et ponit vestimenta sua, et cum accepisset linteum, præcinxit se."
    },
    {
      "n": 5,
      "texto": "Deinde mittit aquam in pelvim, et cœpit lavare pedes discipulorum, et extergere linteo, quo erat præcinctus."
    },
    {
      "n": 6,
      "texto": "Venit ergo ad Simonem Petrum. Et dicit ei Petrus : Domine, tu mihi lavas pedes ?"
    },
    {
      "n": 7,
      "texto": "Respondit Jesus, et dixit ei : Quod ego facio, tu nescis modo : scies autem postea."
    },
    {
      "n": 8,
      "texto": "Dicit ei Petrus : Non lavabis mihi pedes in æternum. Respondit ei Jesus : Si non lavero te, non habebis partem mecum."
    },
    {
      "n": 9,
      "texto": "Dicit ei Simon Petrus : Domine, non tantum pedes meos, sed et manus, et caput."
    },
    {
      "n": 10,
      "texto": "Dicit ei Jesus : Qui lotus est, non indiget nisi ut pedes lavet, sed est mundus totus. Et vos mundi estis, sed non omnes."
    },
    {
      "n": 11,
      "texto": "Sciebat enim quisnam esset qui traderet eum ; propterea dixit : Non estis mundi omnes."
    },
    {
      "n": 12,
      "texto": "Postquam ergo lavit pedes eorum, et accepit vestimenta sua, cum recubuisset iterum, dixit eis : Scitis quid fecerim vobis ?"
    },
    {
      "n": 13,
      "texto": "Vos vocatis me Magister et Domine, et bene dicitis : sum etenim."
    },
    {
      "n": 14,
      "texto": "Si ergo ego lavi pedes vestros, Dominus et Magister, et vos debetis alter alterius lavare pedes."
    },
    {
      "n": 15,
      "texto": "Exemplum enim dedi vobis, ut quemadmodum ego feci vobis, ita et vos faciatis."
    },
    {
      "n": 16,
      "texto": "Amen, amen dico vobis : non est servus major domino suo : neque apostolus major est eo qui misit illum."
    },
    {
      "n": 17,
      "texto": "Si hæc scitis, beati eritis si feceritis ea."
    },
    {
      "n": 18,
      "texto": "Non de omnibus vobis dico : ego scio quos elegerim ; sed ut adimpleatur Scriptura : Qui manducat mecum panem, levabit contra me calcaneum suum."
    },
    {
      "n": 19,
      "texto": "Amodo dico vobis, priusquam fiat : ut cum factum fuerit, credatis quia ego sum."
    },
    {
      "n": 20,
      "texto": "Amen, amen dico vobis : qui accipit si quem misero, me accipit ; qui autem me accipit, accipit eum qui me misit."
    },
    {
      "n": 21,
      "texto": "Cum hæc dixisset Jesus, turbatus est spiritu : et protestatus est, et dixit : Amen, amen dico vobis, quia unus ex vobis tradet me."
    },
    {
      "n": 22,
      "texto": "Aspiciebant ergo ad invicem discipuli, hæsitantes de quo diceret."
    },
    {
      "n": 23,
      "texto": "Erat ergo recumbens unus ex discipulis ejus in sinu Jesu, quem diligebat Jesus."
    },
    {
      "n": 24,
      "texto": "Innuit ergo huic Simon Petrus, et dixit ei : Quis est, de quo dicit ?"
    },
    {
      "n": 25,
      "texto": "Itaque cum recubuisset ille supra pectus Jesu, dicit ei : Domine, quis est ?"
    },
    {
      "n": 26,
      "texto": "Respondit Jesus : Ille est cui ego intinctum panem porrexero. Et cum intinxisset panem, dedit Judæ Simonis Iscariotæ."
    },
    {
      "n": 27,
      "texto": "Et post buccellam, introivit in eum Satanas. Et dixit ei Jesus : Quod facis, fac citius."
    },
    {
      "n": 28,
      "texto": "Hoc autem nemo scivit discumbentium ad quid dixerit ei."
    },
    {
      "n": 29,
      "texto": "Quidam enim putabant, quia loculos habebat Judas, quod dixisset ei Jesus : Eme ea quæ opus sunt nobis ad diem festum : aut egenis ut aliquid daret."
    },
    {
      "n": 30,
      "texto": "Cum ergo accepisset ille buccellam, exivit continuo. Erat autem nox."
    },
    {
      "n": 31,
      "texto": "Cum ergo exisset, dixit Jesus : Nunc clarificatus est Filius hominis, et Deus clarificatus est in eo."
    },
    {
      "n": 32,
      "texto": "Si Deus clarificatus est in eo, et Deus clarificabit eum in semetipso : et continuo clarificabit eum."
    },
    {
      "n": 33,
      "texto": "Filioli, adhuc modicum vobiscum sum. Quæretis me ; et sicut dixi Judæis, quo ego vado, vos non potestis venire : et vobis dico modo."
    },
    {
      "n": 34,
      "texto": "Mandatum novum do vobis : ut diligatis invicem : sicut dilexi vos, ut et vos diligatis invicem."
    },
    {
      "n": 35,
      "texto": "In hoc cognoscent omnes quia discipuli mei estis, si dilectionem habueritis ad invicem."
    },
    {
      "n": 36,
      "texto": "Dicit ei Simon Petrus : Domine, quo vadis ? Respondit Jesus : Quo ego vado non potes me modo sequi : sequeris autem postea."
    },
    {
      "n": 37,
      "texto": "Dicit ei Petrus : Quare non possum te sequi modo ? animam meam pro te ponam."
    },
    {
      "n": 38,
      "texto": "Respondit ei Jesus : Animam tuam pro me pones ? amen, amen dico tibi : non cantabit gallus, donec ter me neges."
    }
  ]
}
